constrain/__init__.py
constrain/api/__init__.py
constrain/api/brick_compliance.py
constrain/api/data_adapter.py
constrain/api/data_processing.py
constrain/api/reporting.py
constrain/api/verification.py
constrain/api/verification_case.py
constrain/api/verification_library.py
constrain/api/workflow.py
constrain/app/README.md
constrain/app/__init__.py
constrain/app/advanced_popup.py
constrain/app/api_to_method.json
constrain/app/app.py
constrain/app/app.spec
constrain/app/components/__init__.py
constrain/app/components/button.py
constrain/app/dependencies.json
constrain/app/extract.py
constrain/app/import_form.py
constrain/app/list_and_choice_popups.py
constrain/app/meta_form.py
constrain/app/popup_window.py
constrain/app/rect_connect.py
constrain/app/schema.json
constrain/app/submit.py
constrain/app/utils.py
constrain/app/workflow_diagram.py
constrain/ashrae.py
constrain/checklib.py
constrain/cli.py
constrain/datapoint.py
constrain/datetimeep.py
constrain/demo/G36_demo/G36_demo_workflow.json
constrain/demo/G36_demo/data/G36_Modelica_Jan.csv
constrain/demo/G36_demo/data/G36_library_verification_cases.json
constrain/demo/G36_demo/g36_demo_workflow_runner.py
constrain/demo/api_demo/demo_dataset.csv
constrain/demo/api_demo/demo_verification_cases.json
constrain/demo/api_demo/demo_workflow.json
constrain/demo/brick_demo/brick_dataset/data_file.csv
constrain/demo/brick_demo/brick_demo_workflow_runner.py
constrain/demo/brick_demo/brick_workflow.json
constrain/demo/library_item_demo/LibraryShowCases.ipynb
constrain/demo/library_item_demo/library_verification_cases.json
constrain/demo/note.txt
constrain/demo/verification_approach_demo/option1/optionsdemo.ipynb
constrain/demo/verification_approach_demo/option2/ASHRAE901_SchoolPrimary_STD2019_ElPaso.csv
constrain/demo/verification_approach_demo/option2/optionsdemo2.ipynb
constrain/demo/verification_approach_demo/option3CNN/Lighting_CNN.html
constrain/demo/verification_approach_demo/option3CNN/Lighting_CNN.ipynb
constrain-0.6.0.dist-info/LICENSE.md
constrain-0.6.0.dist-info/METADATA
constrain-0.6.0.dist-info/WHEEL
constrain-0.6.0.dist-info/entry_points.txt
constrain-0.6.0.dist-info/RECORD
