Metadata-Version: 2.3
Name: ConStrain
Version: 0.6.0
Summary: ConStrain is a data-driven knowledge-integrated framework that automatically verifies that building system controls function as intended.
Author: Lei, Xuechen
Author-email: xuechen.lei@pnnl.gov
Requires-Python: >=3.10,<4.0
Classifier: Programming Language :: Python :: 3
Classifier: Programming Language :: Python :: 3.10
Classifier: Programming Language :: Python :: 3.11
Classifier: Programming Language :: Python :: 3.12
Classifier: Programming Language :: Python :: 3.13
Requires-Dist: black (==24.3.0)
Requires-Dist: brickschema (==0.7.1)
Requires-Dist: click (>=8.1.7,<9.0.0)
Requires-Dist: eppy (>=0.5.63,<0.6.0)
Requires-Dist: fuzzywuzzy (>=0.18.0,<0.19.0)
Requires-Dist: jsonschema (>=4.21.1,<5.0.0)
Requires-Dist: matplotlib (>=3.8.2,<4.0.0)
Requires-Dist: pandas (>=2.1.3,<3.0.0)
Requires-Dist: pre-commit (>=3.6.0,<4.0.0)
Requires-Dist: pydash (>=7.0.6,<8.0.0)
Requires-Dist: pyqt6 (>=6.6.1,<7.0.0)
Requires-Dist: pytest (>=7.4.3,<8.0.0)
Requires-Dist: pyyaml (>=6.0.1,<7.0.0)
Requires-Dist: scikit-learn (>=1.3.2,<2.0.0)
Requires-Dist: scipy (>=1.11.4,<2.0.0)
Requires-Dist: seaborn (>=0.13.0,<0.14.0)
Requires-Dist: tqdm (>=4.66.1,<5.0.0)
Requires-Dist: uuid (>=1.30,<2.0)
